<annotation>
    <folder>upwork</folder>
    <filename>vlcsnap-2020-03-20-13h13m30s496.png</filename>
    <size>
        <width>832</width>
        <height>468</height>
        <depth>3</depth>
    </size>
    <object>
        <name>jockey</name>
        <bndbox>
            <xmin>281</xmin>
            <ymin>84</ymin>
            <xmax>354</xmax>
            <ymax>190</ymax>
        </bndbox>
    </object>
    <object>
        <name>jockey</name>
        <bndbox>
            <xmin>355</xmin>
            <ymin>79</ymin>
            <xmax>433</xmax>
            <ymax>188</ymax>
        </bndbox>
    </object>
    <object>
        <name>jockey</name>
        <bndbox>
            <xmin>428</xmin>
            <ymin>41</ymin>
            <xmax>506</xmax>
            <ymax>158</ymax>
        </bndbox>
    </object>
    <object>
        <name>jockey</name>
        <bndbox>
            <xmin>502</xmin>
            <ymin>73</ymin>
            <xmax>583</xmax>
            <ymax>193</ymax>
        </bndbox>
    </object>
    <object>
        <name>jockey</name>
        <bndbox>
            <xmin>649</xmin>
            <ymin>67</ymin>
            <xmax>736</xmax>
            <ymax>167</ymax>
        </bndbox>
    </object>
</annotation>